READ_mindspore/__init__.py
READ_mindspore/version.py
READ_mindspore/ad_algorithm/_PaDiM.py
READ_mindspore/ad_algorithm/_SPADE.py
READ_mindspore/ad_algorithm/_STPM.py
READ_mindspore/ad_algorithm/__init__.py
READ_mindspore/backbones/__init__.py
READ_mindspore/backbones/_resnet.py
READ_mindspore/datasets/__init__.py
READ_mindspore/datasets/_mvtec.py
READ_mindspore/datasets/_transformations.py
READ_mindspore/optimizer/__init__.py
READ_mindspore/optimizer/_optimizer.py
READ_mindspore/optimizer/_train_step.py
READ_mindspore/scheduler/__init__.py
READ_mindspore/scheduler/_scheduler.py
READ_mindspore/utils/__init__.py
READ_mindspore/utils/_checkpoint_helper.py
READ_mindspore/utils/_gpu_manager.py
READ_mindspore/utils/_image_helper.py
READ_mindspore/utils/_log.py
READ_mindspore/utils/_metrics.py
READ_mindspore-0.1.0.dist-info/LICENSE
READ_mindspore-0.1.0.dist-info/METADATA
READ_mindspore-0.1.0.dist-info/WHEEL
READ_mindspore-0.1.0.dist-info/top_level.txt
READ_mindspore-0.1.0.dist-info/RECORD
