Metadata-Version: 2.1
Name: READ-mindspore
Version: 0.1.0
Summary: Unsupervised Anomaly Localization Toolbox and Benchmark
Home-page: https://git.openi.org.cn/OpenI/READ_mindspore
Author: TCL MV Lab
Author-email: chao46.zhang@tcl.com
License: Apache License 2.0
Platform: UNKNOWN
Classifier: Development Status :: 3 - Alpha
Classifier: License :: OSI Approved :: Apache Software License
Classifier: Operating System :: OS Independent
Classifier: Programming Language :: Python :: 3.6
Classifier: Programming Language :: Python :: 3.7
Classifier: Programming Language :: Python :: 3.8
Requires-Python: >=3, <4
Requires-Dist: tqdm
Requires-Dist: numpy
Requires-Dist: pandas
Requires-Dist: scipy
Requires-Dist: kornia (>=0.5.0)
Requires-Dist: matplotlib (>=3.3.4)
Requires-Dist: albumentations (==0.5.2)
Requires-Dist: einops (>=0.3.0)
Requires-Dist: scikit-learn (>=0.24.2)
Requires-Dist: scikit-image (>=0.18.1)
Requires-Dist: mindspore (==1.3.0)
